dj/choicee/__init__.py
dj/choicee/core.py
dj/choicee/fields.py
dj/choicee/more.py
dj.choicee-0.9.2.dist-info/WHEEL
dj.choicee-0.9.2.dist-info/METADATA
dj.choicee-0.9.2.dist-info/RECORD
