Metadata-Version: 2.1
Name: dj.choicee
Version: 0.9.2
Summary: An enum implementation for Django field choices, supporting group
Home-page: https://github.com/AgriConnect/dj.choicee
License: MIT
Author: Nguyễn Hồng Quân
Author-email: ng.hong.quan@gmail.com
Maintainer: Nguyễn Hồng Quân
Maintainer-email: ng.hong.quan@gmail.com
Requires-Python: >=3.5
Classifier: Development Status :: 5 - Production/Stable
Classifier: Framework :: Django
Classifier: License :: OSI Approved :: MIT License
Classifier: Natural Language :: English
Classifier: Programming Language :: Python
Classifier: Programming Language :: Python :: 3
Classifier: Programming Language :: Python :: 3.5
Classifier: Programming Language :: Python :: 3.6
Classifier: Programming Language :: Python :: 3.7
Classifier: Programming Language :: Python :: 3.8
Classifier: Topic :: Internet :: WWW/HTTP
Classifier: Topic :: Software Development :: Libraries :: Python Modules
Requires-Dist: django (>=2.0)
Project-URL: Repository, https://github.com/AgriConnect/dj.choicee.git
